odoo/addons/pos_auto_invoice_company/README.rst
odoo/addons/pos_auto_invoice_company/__init__.py
odoo/addons/pos_auto_invoice_company/__manifest__.py
odoo/addons/pos_auto_invoice_company/i18n/pos_auto_invoice_company.pot
odoo/addons/pos_auto_invoice_company/readme/CONTRIBUTORS.rst
odoo/addons/pos_auto_invoice_company/readme/DESCRIPTION.rst
odoo/addons/pos_auto_invoice_company/static/description/index.html
odoo/addons/pos_auto_invoice_company/static/src/css/pos_auto_invoice_company.css
odoo/addons/pos_auto_invoice_company/static/src/js/pos_auto_invoice_company.js
odoo/addons/pos_auto_invoice_company/views/assets.xml
odoo12_addon_pos_auto_invoice_company-12.0.3.0.0.dist-info/METADATA
odoo12_addon_pos_auto_invoice_company-12.0.3.0.0.dist-info/WHEEL
odoo12_addon_pos_auto_invoice_company-12.0.3.0.0.dist-info/top_level.txt
odoo12_addon_pos_auto_invoice_company-12.0.3.0.0.dist-info/RECORD
