Metadata-Version: 2.1
Name: odoo12-addon-pos_auto_invoice_company
Version: 12.0.3.0.0
Summary: Applies to_invoice to company partners.
Home-page: https://github.com/beescoop/Obeesdoo
Author: BEES coop - Cellule IT, Coop IT Easy SC
License: AGPL-3
Classifier: Programming Language :: Python
Classifier: Framework :: Odoo
Classifier: Framework :: Odoo :: 12.0
Classifier: License :: OSI Approved :: GNU Affero General Public License v3
Requires-Python: >=3.5
Requires-Dist: odoo<12.1dev,>=12.0a
